[
  {
    "title": "Software",
    "description": "Realizziamo software con tecnoligie altamente performanti",
    "icon": "fa-solid fa-microchip"
  },
  {
    "title": "Open Business",
    "description": "Una impresa Open Business",
    "icon": "fa-solid fa-hand-holding-heart",
    "link": "https://en.wikipedia.org/wiki/Open_business"
  },
  {
    "title": "Open source",
    "description": "Tutti i nostri progetti sono open source! Guardali su Github",
    "icon": "fa-brands fa-github",
    "link": "https://github.com/UtopiaTechIT"
  }
]